NumberCommutation/Pyrisky.py
NumberCommutation/__init__.py
NumberCommutation-0.0.3.dist-info/LICENCE
NumberCommutation-0.0.3.dist-info/METADATA
NumberCommutation-0.0.3.dist-info/WHEEL
NumberCommutation-0.0.3.dist-info/top_level.txt
NumberCommutation-0.0.3.dist-info/RECORD
