Metadata-Version: 2.1
Name: NumberCommutation
Version: 0.0.3
Summary: Um agrupamento de calculos atuariais
Author: Pedro Cavalcante
Author-email: ph.cavalcante29@gmail.com
License: MIT License
Keywords: Matemática Atuarial,Números de comutação
License-File: LICENCE
Requires-Dist: pandas
Requires-Dist: numpy
